moatless/.gitignore
moatless/__init__.py
moatless/actions/__init__.py
moatless/actions/action.py
moatless/actions/apply_change_and_test.py
moatless/actions/code_action_value_mixin.py
moatless/actions/code_change.py
moatless/actions/code_modification_mixin.py
moatless/actions/create_file.py
moatless/actions/edit.py
moatless/actions/find_class.py
moatless/actions/find_code_snippet.py
moatless/actions/find_function.py
moatless/actions/finish.py
moatless/actions/insert_line.py
moatless/actions/model.py
moatless/actions/reject.py
moatless/actions/request_context.py
moatless/actions/run_tests.py
moatless/actions/search_base.py
moatless/actions/semantic_search.py
moatless/actions/string_replace.py
moatless/agent/__init__.py
moatless/agent/agent.py
moatless/agent/code_agent.py
moatless/agent/code_prompts.py
moatless/benchmark/__init__.py
moatless/benchmark/create_dataset.py
moatless/benchmark/evaluation.py
moatless/benchmark/evaluation_dataset.csv
moatless/benchmark/report.py
moatless/benchmark/run_evaluation.py
moatless/benchmark/swebench/__init__.py
moatless/benchmark/swebench/utils.py
moatless/benchmark/swebench_lite_all_evaluations.json
moatless/benchmark/swebench_verified_all_evaluations.json
moatless/benchmark/utils.py
moatless/codeblocks/__init__.py
moatless/codeblocks/codeblocks.py
moatless/codeblocks/module.py
moatless/codeblocks/parser/__init__.py
moatless/codeblocks/parser/comment.py
moatless/codeblocks/parser/create.py
moatless/codeblocks/parser/java.py
moatless/codeblocks/parser/parser.py
moatless/codeblocks/parser/python.py
moatless/codeblocks/parser/queries/__init__.py
moatless/codeblocks/parser/queries/java.scm
moatless/codeblocks/parser/queries/python.scm
moatless/codeblocks/parser/queries/python_gpt.scm
moatless/completion/__init__.py
moatless/completion/completion.py
moatless/completion/log_handler.py
moatless/completion/model.py
moatless/debate.py
moatless/discriminator.py
moatless/exceptions.py
moatless/feedback.py
moatless/file_context.py
moatless_tree_search-0.0.4.dist-info/LICENSE
moatless_tree_search-0.0.4.dist-info/METADATA
moatless_tree_search-0.0.4.dist-info/WHEEL
moatless_tree_search-0.0.4.dist-info/entry_points.txt
moatless_tree_search-0.0.4.dist-info/RECORD
