Metadata-Version: 2.1
Name: moatless-tree-search
Version: 0.0.4
Summary: 
Author: Albert Örwall
Author-email: albert@moatless.ai
Requires-Python: >=3.10,<=3.13
Classifier: Programming Language :: Python :: 3
Classifier: Programming Language :: Python :: 3.10
Classifier: Programming Language :: Python :: 3.11
Classifier: Programming Language :: Python :: 3.12
Requires-Dist: anthropic (>=0.38.0,<0.39.0)
Requires-Dist: boto3 (>=1.35.54,<2.0.0)
Requires-Dist: botocore (>=1.35.54,<2.0.0)
Requires-Dist: faiss-cpu (>=1.8.0.post1,<2.0.0)
Requires-Dist: gitpython (>=3.1.43,<4.0.0)
Requires-Dist: instructor (>=1.3.7,<2.0.0)
Requires-Dist: jsonref (>=1.1.0,<2.0.0)
Requires-Dist: litellm (>=1.51.2,<2.0.0)
Requires-Dist: llama-index (>=0.10.65,<0.11.0)
Requires-Dist: llama-index-embeddings-openai (>=0.1.11,<0.2.0)
Requires-Dist: llama-index-embeddings-voyageai (>=0.1.4,<0.2.0)
Requires-Dist: llama-index-readers-file (>=0.1.33,<0.2.0)
Requires-Dist: matplotlib (>=3.9.2,<4.0.0)
Requires-Dist: networkx (>=3.3,<4.0)
Requires-Dist: numpy (>=1.0,<2.0)
Requires-Dist: openai (>=1.41.0,<2.0.0)
Requires-Dist: pandas (>=2.2.2,<3.0.0)
Requires-Dist: plotly (>=5.24.0,<6.0.0)
Requires-Dist: pyarrow (>=17.0.0,<18.0.0)
Requires-Dist: pydantic (>=2.8.2,<3.0.0)
Requires-Dist: pygraphviz (>=1.14,<2.0)
Requires-Dist: pylint (>=3.2.6,<4.0.0)
Requires-Dist: rapidfuzz (>=3.9.5,<4.0.0)
Requires-Dist: scipy (>=1.14.0,<2.0.0)
Requires-Dist: streamlit (>=1.38.0,<2.0.0)
Requires-Dist: tenacity (>=8.2.0,<9.0.0)
Requires-Dist: tiktoken (>=0.7.0,<0.8.0)
Requires-Dist: tree-sitter (==0.22.3)
Requires-Dist: tree-sitter-java (==0.21.0)
Requires-Dist: tree-sitter-python (==0.21.0)
Requires-Dist: unidiff (>=0.7.5,<0.8.0)
